famly_fetch/__init__.py
famly_fetch/api_client.py
famly_fetch/cli.py
famly_fetch/downloader.py
famly_fetch/image.py
famly_fetch/graphql/Authenticate.graphql
famly_fetch/graphql/GetChildNotes.graphql
famly_fetch/graphql/LearningJourneyQuery.graphql
famly_fetch-0.3.0.dist-info/licenses/LICENSE
famly_fetch-0.3.0.dist-info/METADATA
famly_fetch-0.3.0.dist-info/WHEEL
famly_fetch-0.3.0.dist-info/entry_points.txt
famly_fetch-0.3.0.dist-info/top_level.txt
famly_fetch-0.3.0.dist-info/RECORD
