Metadata-Version: 2.4
Name: famly-fetch
Version: 0.3.0
Summary: Fetch your (kid's) images from famly.co
Author: Jacob Bunk Nielsen, Morten Siebuhr, iLeoDo, Tom Vincent
Classifier: Programming Language :: Python :: 3
Classifier: License :: OSI Approved :: MIT License
Classifier: Operating System :: OS Independent
Requires-Python: >=3.7
License-File: LICENSE
Requires-Dist: piexif==1.1.3
Requires-Dist: click
Requires-Dist: importlib-resources
Provides-Extra: dev
Requires-Dist: ruff; extra == "dev"
Requires-Dist: build; extra == "dev"
Requires-Dist: twine; extra == "dev"
Dynamic: license-file
